django_flyio/__init__.py
django_flyio/db.py
django_flyio/middleware.py
django_flyio/py.typed
django_flyio/routers.py
django_flyio-0.1.1.dist-info/METADATA
django_flyio-0.1.1.dist-info/WHEEL
django_flyio-0.1.1.dist-info/licenses/LICENSE
django_flyio-0.1.1.dist-info/RECORD
