Metadata-Version: 2.1
Name: django-flyio
Version: 0.1.1
Summary: A set of simple utilities for Django apps running on Fly.io
Project-URL: Documentation, https://github.com/joshuadavidthomas/django-flyio#readme
Project-URL: Issues, https://github.com/joshuadavidthomas/django-flyio/issues
Project-URL: Source, https://github.com/joshuadavidthomas/django-flyio
Author-email: Josh <josh@joshthomas.dev>
License-Expression: MIT
License-File: LICENSE
Classifier: Development Status :: 4 - Beta
Classifier: License :: OSI Approved :: MIT License
Classifier: Operating System :: OS Independent
Classifier: Programming Language :: Python
Classifier: Programming Language :: Python :: 3
Classifier: Programming Language :: Python :: 3 :: Only
Classifier: Programming Language :: Python :: 3.7
Classifier: Programming Language :: Python :: 3.8
Classifier: Programming Language :: Python :: 3.9
Classifier: Programming Language :: Python :: 3.10
Classifier: Programming Language :: Python :: 3.11
Classifier: Programming Language :: Python :: Implementation :: CPython
Requires-Python: >=3.7
Requires-Dist: dj-database-url
Requires-Dist: django>=3.2
Provides-Extra: dev
Requires-Dist: black; extra == 'dev'
Requires-Dist: hatch; extra == 'dev'
Requires-Dist: ruff; extra == 'dev'
Provides-Extra: test
Requires-Dist: coverage[toml]; extra == 'test'
Requires-Dist: pytest; extra == 'test'
Requires-Dist: pytest-asyncio; extra == 'test'
Requires-Dist: pytest-django; extra == 'test'
Provides-Extra: types
Requires-Dist: django-stubs; extra == 'types'
Requires-Dist: mypy; extra == 'types'
